eb_optimization/__init__.py
eb_optimization/_utils.py
eb_optimization/policies/__init__.py
eb_optimization/policies/cost_ratio_policy.py
eb_optimization/policies/dqc_policy.py
eb_optimization/policies/evaluation.py
eb_optimization/policies/ral_policy.py
eb_optimization/policies/tau_policy.py
eb_optimization/search/__init__.py
eb_optimization/search/grid.py
eb_optimization/search/kernels.py
eb_optimization/tuning/__init__.py
eb_optimization/tuning/cost_ratio.py
eb_optimization/tuning/ral.py
eb_optimization/tuning/sensitivity.py
eb_optimization/tuning/tau.py
eb_optimization-0.2.5.dist-info/licenses/LICENSE
eb_optimization-0.2.5.dist-info/METADATA
eb_optimization-0.2.5.dist-info/WHEEL
eb_optimization-0.2.5.dist-info/top_level.txt
eb_optimization-0.2.5.dist-info/RECORD
