Metadata-Version: 2.4
Name: eb-optimization
Version: 0.2.5
Summary: Electric Barometer: Optimization and tuning utilities for EB objectives and policy parameters.
Author-email: "Kyle Corrie (Economistician)" <kcorrie@economistician.com>
License-Expression: BSD-3-Clause
Project-URL: Homepage, https://github.com/Economistician/eb-optimization
Project-URL: Repository, https://github.com/Economistician/eb-optimization
Project-URL: Issues, https://github.com/Economistician/eb-optimization/issues
Project-URL: Documentation, https://github.com/Economistician/eb-docs
Keywords: electric-barometer,optimization,tuning,grid-search,calibration,asymmetric-loss,forecasting,pandas
Classifier: Programming Language :: Python :: 3
Classifier: Programming Language :: Python :: 3 :: Only
Classifier: Programming Language :: Python :: 3.10
Classifier: Programming Language :: Python :: 3.11
Classifier: Programming Language :: Python :: 3.12
Classifier: Programming Language :: Python :: 3.13
Classifier: Operating System :: OS Independent
Requires-Python: >=3.10
License-File: LICENSE
Requires-Dist: numpy>=1.24
Requires-Dist: pandas>=2.0
Requires-Dist: eb-metrics<0.3,>=0.2
Provides-Extra: eb
Requires-Dist: eb-metrics<0.3,>=0.2; extra == "eb"
Requires-Dist: eb-evaluation<0.3,>=0.2; extra == "eb"
Provides-Extra: opt
Provides-Extra: test
Requires-Dist: pytest>=8.0; extra == "test"
Requires-Dist: scikit-learn>=1.3; extra == "test"
Provides-Extra: dev
Requires-Dist: pytest>=8.0; extra == "dev"
Requires-Dist: pytest-cov>=5.0; extra == "dev"
Requires-Dist: ruff>=0.0.1; extra == "dev"
Requires-Dist: pyright>=1.1; extra == "dev"
Requires-Dist: twine>=4.0; extra == "dev"
Provides-Extra: all
Requires-Dist: eb-metrics<0.3,>=0.2; extra == "all"
Requires-Dist: eb-evaluation<0.3,>=0.2; extra == "all"
Requires-Dist: pytest>=8.0; extra == "all"
Requires-Dist: scikit-learn>=1.3; extra == "all"
Requires-Dist: pytest-cov>=5.0; extra == "all"
Requires-Dist: ruff>=0.0.1; extra == "all"
Requires-Dist: pyright>=1.1; extra == "all"
Requires-Dist: twine>=4.0; extra == "all"
Dynamic: license-file
